pahud_cdktf_aws_eks/__init__.py
pahud_cdktf_aws_eks/py.typed
pahud_cdktf_aws_eks/_jsii/__init__.py
pahud_cdktf_aws_eks/_jsii/cdktf-aws-eks@0.3.0.jsii.tgz
pahud_cdktf_aws_eks-0.3.0.dist-info/LICENSE
pahud_cdktf_aws_eks-0.3.0.dist-info/METADATA
pahud_cdktf_aws_eks-0.3.0.dist-info/WHEEL
pahud_cdktf_aws_eks-0.3.0.dist-info/top_level.txt
pahud_cdktf_aws_eks-0.3.0.dist-info/RECORD
