Metadata-Version: 2.1
Name: pahud-cdktf-aws-eks
Version: 0.3.0
Summary: CDKTF construct library for Amazon EKS
Home-page: https://github.com/pahud/cdktf-aws-eks
Author: Pahud Hsieh<pahudnet@gmail.com>
License: Apache-2.0
Project-URL: Source, https://github.com/pahud/cdktf-aws-eks
Platform: UNKNOWN
Classifier: Intended Audience :: Developers
Classifier: Operating System :: OS Independent
Classifier: Programming Language :: JavaScript
Classifier: Programming Language :: Python :: 3 :: Only
Classifier: Programming Language :: Python :: 3.6
Classifier: Programming Language :: Python :: 3.7
Classifier: Programming Language :: Python :: 3.8
Classifier: Programming Language :: Python :: 3.9
Classifier: Typing :: Typed
Classifier: Development Status :: 5 - Production/Stable
Classifier: License :: OSI Approved
Requires-Python: >=3.6
License-File: LICENSE
Requires-Dist: cdktf-cdktf-provider-aws (<4.0.0,>=3.0.1)
Requires-Dist: cdktf-cdktf-provider-kubernetes (<0.5.0,>=0.4.29)
Requires-Dist: cdktf (<0.9.0,>=0.8.1)
Requires-Dist: constructs (<11.0.0,>=10.0.0)
Requires-Dist: jsii (<2.0.0,>=1.39.0)
Requires-Dist: publication (>=0.0.3)
